{
  "version": 1,
  "project": "minecraft",
  "personality": {
    "observations": [],
    "working_style": [],
    "preferences": [],
    "projects_known": [],
    "communication": "",
    "updated": "2026-06-11T16:34:59.500Z"
  },
  "knowledge": [],
  "dead_ends": [],
  "working_context": {
    "current_task": "Awaiting initial conversation",
    "progress": "System initialized and awaiting input.",
    "next_steps": "Provide conversation text to begin knowledge extraction.",
    "blockers": "No conversation has been provided yet for analysis.",
    "updated": "2026-06-12T04:34:32.431Z"
  },
  "observations": [],
  "stats": {
    "total_extractions": 3,
    "total_memories": 0,
    "total_sessions": 2,
    "last_session": "2026-06-12T15:51:03.800Z",
    "last_extraction": "2026-06-12T17:17:51.254Z"
  }
}